c64py/C64.py
c64py/__init__.py
c64py/constants.py
c64py/cpu.py
c64py/cpu_state.py
c64py/debug.py
c64py/emulator.py
c64py/graphics.py
c64py/memory.py
c64py/roms.py
c64py/server.py
c64py/ui.py
c64py-0.1.0.dist-info/licenses/LICENSE
c64py-0.1.0.dist-info/METADATA
c64py-0.1.0.dist-info/WHEEL
c64py-0.1.0.dist-info/entry_points.txt
c64py-0.1.0.dist-info/top_level.txt
c64py-0.1.0.dist-info/RECORD
