Metadata-Version: 2.4
Name: c64py
Version: 0.1.0
Summary: A Commodore 64 emulator implemented in Python with a text-based interface.
Author: c64py contributors
License-Expression: BSD-3-Clause
Project-URL: Homepage, https://github.com/luar/c64py
Classifier: Development Status :: 3 - Alpha
Classifier: Intended Audience :: Developers
Classifier: Programming Language :: Python :: 3
Classifier: Programming Language :: Python :: 3 :: Only
Classifier: Programming Language :: Python :: 3.9
Classifier: Programming Language :: Python :: 3.10
Classifier: Programming Language :: Python :: 3.11
Classifier: Programming Language :: Python :: 3.12
Requires-Python: >=3.9
License-File: LICENSE
Requires-Dist: rich>=13.0.0
Requires-Dist: textual>=0.40.0
Requires-Dist: pygame>=2.6.1
Dynamic: license-file
